<?xml version="1.0" encoding="UTF-8" standalone="yes"?>
<CMapData>
  <name>krapea_lod</name>
  <parent/>
  <flags value="2"/>
  <contentFlags value="2"/>
  <streamingExtentsMin x="-633.9512033961264" y="-779.8381867506998" z="-878.76916"/>
  <streamingExtentsMax x="1377.0726966038737" y="1229.4108332493001" z="1127.869"/>
  <entitiesExtentsMin x="366.04879660387365" y="220.16181324930017" z="121.23084"/>
  <entitiesExtentsMax x="377.0726966038736" y="229.41083324930017" z="127.869"/>
  <entities>
    <Item type="CEntityDef">
      <archetypeName>krapea_lod</archetypeName>
      <flags value="1572864"/>
      <guid value="0"/>
      <position x="371.5607466038736" y="224.78632324930015" z="124.54992"/>
      <rotation x="0" y="0" z="-0.9397029113635912" w="0.3419918688723324"/>
      <scaleXY value="1"/>
      <scaleZ value="1"/>
      <parentIndex value="-1"/>
      <lodDist value="1000"/>
      <childLodDist value="95"/>
      <lodLevel>LODTYPES_DEPTH_SLOD1</lodLevel>
      <numChildren value="1"/>
      <priorityLevel>PRI_REQUIRED</priorityLevel>
      <extensions/>
      <ambientOcclusionMultiplier value="255"/>
      <artificialAmbientOcclusion value="255"/>
      <tintValue value="0"/>
    </Item>
  </entities>
  <containerLods/>
  <boxOccluders/>
  <occludeModels/>
  <physicsDictionaries/>
  <instancedData>
    <ImapLink/>
    <PropInstanceList/>
    <GrassInstanceList/>
  </instancedData>
  <timeCycleModifiers/>
  <carGenerators/>
  <LODLightsSOA>
    <direction/>
    <falloff/>
    <falloffExponent/>
    <timeAndStateFlags/>
    <hash/>
    <coneInnerAngle/>
    <coneOuterAngleOrCapExt/>
    <coronaIntensity/>
  </LODLightsSOA>
  <DistantLODLightsSOA>
    <position/>
    <RGBI/>
    <numStreetLights value="0"/>
    <category value="0"/>
  </DistantLODLightsSOA>
  <block>
    <version value="0"/>
    <flags value="0"/>
    <name>krapea_lod</name>
    <owner/>
  </block>
</CMapData>