<?xml version="1.0" encoding="UTF-8" standalone="yes"?>
<CMapTypes>
  <extensions/>
  <archetypes>
    <Item type="CBaseArchetypeDef">
      <lodDist value="1000"/>
      <flags value="0"/>
      <specialAttribute value="0"/>
      <bbMin x="-14.398031633872735" y="-0.0001" z="-6.692359999999999"/>
      <bbMax x="14.398031633872735" y="0.0001" z="6.692359999999999"/>
      <bsCentre x="0" y="0" z="0"/>
      <bsRadius value="14.398031633872735"/>
      <hdTextureDist value="1000"/>
      <name>obey1_lod</name>
      <textureDictionary>obey1_lod</textureDictionary>
      <clipDictionary/>
      <drawableDictionary/>
      <physicsDictionary/>
      <assetType>ASSET_TYPE_DRAWABLE</assetType>
      <assetName>obey1_lod</assetName>
      <extensions/>
    </Item>
  </archetypes>
  <name/>
  <dependencies/>
  <compositeEntityTypes/>
</CMapTypes>